phrase_counter/__init__.py
phrase_counter/cleaner.py
phrase_counter/ingest.py
phrase_counter/static/stop-words.txt
phrase_counter/word_graph.py
phrase_counter-0.2.6.dist-info/LICENSE
phrase_counter-0.2.6.dist-info/WHEEL
phrase_counter-0.2.6.dist-info/METADATA
phrase_counter-0.2.6.dist-info/RECORD
