Metadata-Version: 2.1
Name: phrase-counter
Version: 0.2.6
Summary: Counting stop words.
Home-page: https://github.com/rezashabrang/stop-word-counter
License: MIT
Author: aasaam
Author-email: rezashabrang.m@gmail.com
Requires-Python: >=3.8,<4.0
Classifier: Development Status :: 3 - Alpha
Classifier: Intended Audience :: Developers
Classifier: License :: OSI Approved :: MIT License
Classifier: Operating System :: OS Independent
Classifier: Programming Language :: Python :: 3
Classifier: Programming Language :: Python :: 3.10
Classifier: Programming Language :: Python :: 3.8
Classifier: Programming Language :: Python :: 3.9
Classifier: Topic :: Software Development :: Libraries :: Python Modules
Requires-Dist: PyICU (>=2.8.1,<3.0.0)
Requires-Dist: beautifulsoup4
Requires-Dist: cleaning-utils (>=0.1.5,<0.2.0)
Requires-Dist: importlib_metadata (>=4.5.0,<5.0.0); python_version < "3.8"
Requires-Dist: pandas
Requires-Dist: polyglot
Requires-Dist: pycld2 (>=0.41,<0.42)
Requires-Dist: requests
Requires-Dist: scikit-learn
Project-URL: Repository, https://github.com/rezashabrang/stop-word-counter
